{
   "_typeName" : "TextBank",
   "_version" : "VER3",
   "database" : [
      {
         "_key" : "01",
         "_value" : "Позволяет вашему герою изучить заклинания первого круга"
      },
      {
         "_key" : "01_name",
         "_value" : "Гильдия магии первого уровня"
      },
      {
         "_key" : "02",
         "_value" : "Позволяет вашему герою изучить заклинания второго круга"
      },
      {
         "_key" : "02_name",
         "_value" : "Гильдия магии второго уровня"
      },
      {
         "_key" : "03",
         "_value" : "Позволяет вашему герою изучить заклинания третьего круга"
      },
      {
         "_key" : "03_name",
         "_value" : "Гильдия магии третьего уровня"
      },
      {
         "_key" : "04",
         "_value" : "Позволяет вашему герою изучить заклинания четвертого круга"
      },
      {
         "_key" : "04_name",
         "_value" : "Храм Христа спасителя"
      },
      {
         "_key" : "11",
         "_value" : "Позволяет нанимать в городе копейщиков"
      },
      {
         "_key" : "11_name",
         "_value" : "Гарнизон"
      },
      {
         "_key" : "12",
         "_value" : "Позволяет нанимать в городе лучников"
      },
      {
         "_key" : "12_name",
         "_value" : "Башня лучников"
      },
      {
         "_key" : "13",
         "_value" : "Позволяет нанимать в городе грифонов"
      },
      {
         "_key" : "13_name",
         "_value" : "Башня грифонов"
      },
      {
         "_key" : "14",
         "_value" : "Позволяет нанимать в городе инквизиторов"
      },
      {
         "_key" : "14_name",
         "_value" : "Монастырь"
      },
      {
         "_key" : "15",
         "_value" : "Позволяет нанимать в городе паладинов"
      },
      {
         "_key" : "15_name",
         "_value" : "Орден паладинов"
      },
      {
         "_key" : "16",
         "_value" : "Позволяет нанимать в городе ангелов"
      },
      {
         "_key" : "16_name",
         "_value" : "Цитадель"
      },
      {
         "_key" : "20",
         "_value" : "Даёт 250 золота за ход"
      },
      {
         "_key" : "20_name",
         "_value" : "Дом старейшин"
      },
      {
         "_key" : "21",
         "_value" : "Даёт 1000 золота за ход"
      },
      {
         "_key" : "21_name",
         "_value" : "Ратуша"
      },
      {
         "_key" : "22",
         "_value" : "Даёт 2000 золота за ход"
      },
      {
         "_key" : "22_name",
         "_value" : "Магистрат"
      },
      {
         "_key" : "23",
         "_value" : "Даёт 4000 золота за ход"
      },
      {
         "_key" : "23_name",
         "_value" : "Капитолий"
      }
   ]
}
